odoo/addons/l10n_us_form_1099/README.rst
odoo/addons/l10n_us_form_1099/__init__.py
odoo/addons/l10n_us_form_1099/__manifest__.py
odoo/addons/l10n_us_form_1099/data/box_1099_misc_data.xml
odoo/addons/l10n_us_form_1099/data/type_1099_data.xml
odoo/addons/l10n_us_form_1099/i18n/es.po
odoo/addons/l10n_us_form_1099/i18n/l10n_us_form_1099.pot
odoo/addons/l10n_us_form_1099/i18n/nl_NL.po
odoo/addons/l10n_us_form_1099/models/__init__.py
odoo/addons/l10n_us_form_1099/models/box_1099_misc.py
odoo/addons/l10n_us_form_1099/models/res_partner.py
odoo/addons/l10n_us_form_1099/models/type_1099.py
odoo/addons/l10n_us_form_1099/readme/CONFIGURE.md
odoo/addons/l10n_us_form_1099/readme/CONTRIBUTORS.md
odoo/addons/l10n_us_form_1099/readme/CREDITS.md
odoo/addons/l10n_us_form_1099/readme/DESCRIPTION.md
odoo/addons/l10n_us_form_1099/readme/USAGE.md
odoo/addons/l10n_us_form_1099/reports/__init__.py
odoo/addons/l10n_us_form_1099/reports/account_payment_1099_report.py
odoo/addons/l10n_us_form_1099/reports/account_payment_1099_report_views.xml
odoo/addons/l10n_us_form_1099/security/ir.model.access.csv
odoo/addons/l10n_us_form_1099/static/description/icon.png
odoo/addons/l10n_us_form_1099/static/description/index.html
odoo/addons/l10n_us_form_1099/static/description/l10n_us_form_1099.svg
odoo/addons/l10n_us_form_1099/views/box_1099_misc_views.xml
odoo/addons/l10n_us_form_1099/views/res_partner_views.xml
odoo/addons/l10n_us_form_1099/views/type_1099_views.xml
odoo_addon_l10n_us_form_1099-17.0.1.0.0.5.dist-info/METADATA
odoo_addon_l10n_us_form_1099-17.0.1.0.0.5.dist-info/WHEEL
odoo_addon_l10n_us_form_1099-17.0.1.0.0.5.dist-info/top_level.txt
odoo_addon_l10n_us_form_1099-17.0.1.0.0.5.dist-info/RECORD
